MANIFEST.in
README.txt
setup.py
docs/HISTORY.txt
src/smitheme/__init__.py
src/smitheme.industrial.egg-info/PKG-INFO
src/smitheme.industrial.egg-info/SOURCES.txt
src/smitheme.industrial.egg-info/dependency_links.txt
src/smitheme.industrial.egg-info/namespace_packages.txt
src/smitheme.industrial.egg-info/not-zip-safe
src/smitheme.industrial.egg-info/requires.txt
src/smitheme.industrial.egg-info/top_level.txt
src/smitheme/industrial/__init__.py
src/smitheme/industrial/configure.zcml
src/smitheme/industrial/icon.py
src/smitheme/industrial/skin.py
src/smitheme/industrial/static/css/actions.css
src/smitheme/industrial/static/css/actions.min.css
src/smitheme/industrial/static/css/forms.css
src/smitheme/industrial/static/css/forms.min.css
src/smitheme/industrial/static/css/formwidgets.css
src/smitheme/industrial/static/css/formwidgets.min.css
src/smitheme/industrial/static/css/jstree.css
src/smitheme/industrial/static/css/jstree.min.css
src/smitheme/industrial/static/css/listing.css
src/smitheme/industrial/static/css/listing.min.css
src/smitheme/industrial/static/css/navigation.css
src/smitheme/industrial/static/css/navigation.min.css
src/smitheme/industrial/static/css/smi.css
src/smitheme/industrial/static/css/smi.min.css
src/smitheme/industrial/static/css/style.css
src/smitheme/industrial/static/css/style.min.css
src/smitheme/industrial/static/img/apple-touch-icon.png
src/smitheme/industrial/static/img/arrow-down.png
src/smitheme/industrial/static/img/gear.png
src/smitheme/industrial/static/img/gradient-tab-selected.png
src/smitheme/industrial/static/img/gradient-tab.png
src/smitheme/industrial/static/img/gradient-tab2.png
src/smitheme/industrial/static/img/gradient20m.png
src/smitheme/industrial/static/img/gradient25.png
src/smitheme/industrial/static/img/gradient25d.png
src/smitheme/industrial/static/img/gradient50.png
src/smitheme/industrial/static/img/gradient50d.png
src/smitheme/industrial/static/img/gradient75.png
src/smitheme/industrial/static/img/gradientblack.png
src/smitheme/industrial/static/img/heading_bg.png
src/smitheme/industrial/static/img/loader.gif
src/smitheme/industrial/static/img/loading.gif
src/smitheme/industrial/static/img/overlay.png
src/smitheme/industrial/static/img/settings.png
src/smitheme/industrial/static/img/silva.ico
src/smitheme/industrial/static/img/silva.png
