Metadata-Version: 1.1
Name: smitheme.industrial
Version: 3.0
Summary: Alternate (original) SMI Skin for Silva 3.0
Home-page: https://github.com/silvacms/smitheme.industrial
Author: Infrae
Author-email: info@infrae.com
License: BSD
Keywords: skin silva smi
Platform: UNKNOWN
Classifier: Programming Language :: Python
Classifier: Topic :: Software Development :: Libraries :: Python Modules
